{"ast":null,"code":"var debug = require('debug')('algoliasearch:src/hostIndexState.js');\n\nvar localStorageNamespace = 'algoliasearch-client-js';\nvar store;\nvar moduleStore = {\n  state: {},\n  set: function set(key, data) {\n    this.state[key] = data;\n    return this.state[key];\n  },\n  get: function get(key) {\n    return this.state[key] || null;\n  }\n};\nvar localStorageStore = {\n  set: function set(key, data) {\n    moduleStore.set(key, data); // always replicate localStorageStore to moduleStore in case of failure\n\n    try {\n      var namespace = JSON.parse(global.localStorage[localStorageNamespace]);\n      namespace[key] = data;\n      global.localStorage[localStorageNamespace] = JSON.stringify(namespace);\n      return namespace[key];\n    } catch (e) {\n      return localStorageFailure(key, e);\n    }\n  },\n  get: function get(key) {\n    try {\n      return JSON.parse(global.localStorage[localStorageNamespace])[key] || null;\n    } catch (e) {\n      return localStorageFailure(key, e);\n    }\n  }\n};\n\nfunction localStorageFailure(key, e) {\n  debug('localStorage failed with', e);\n  cleanup();\n  store = moduleStore;\n  return store.get(key);\n}\n\nstore = supportsLocalStorage() ? localStorageStore : moduleStore;\nmodule.exports = {\n  get: getOrSet,\n  set: getOrSet,\n  supportsLocalStorage: supportsLocalStorage\n};\n\nfunction getOrSet(key, data) {\n  if (arguments.length === 1) {\n    return store.get(key);\n  }\n\n  return store.set(key, data);\n}\n\nfunction supportsLocalStorage() {\n  try {\n    if ('localStorage' in global && global.localStorage !== null) {\n      if (!global.localStorage[localStorageNamespace]) {\n        // actual creation of the namespace\n        global.localStorage.setItem(localStorageNamespace, JSON.stringify({}));\n      }\n\n      return true;\n    }\n\n    return false;\n  } catch (_) {\n    return false;\n  }\n} // In case of any error on localStorage, we clean our own namespace, this should handle\n// quota errors when a lot of keys + data are used\n\n\nfunction cleanup() {\n  try {\n    global.localStorage.removeItem(localStorageNamespace);\n  } catch (_) {// nothing to do\n  }\n}","map":null,"metadata":{},"sourceType":"module"}